setup.py
txyam/__init__.py
txyam/client.py
txyam/factory.py
txyam/sync.py
txyam/utils.py
txyam/test/__init__.py
txyam/test/test_client.py
txyam2.egg-info/PKG-INFO
txyam2.egg-info/SOURCES.txt
txyam2.egg-info/dependency_links.txt
txyam2.egg-info/requires.txt
txyam2.egg-info/top_level.txt