Metadata-Version: 2.1
Name: txyam2
Version: 0.5.1
Summary: Yet Another Memcached (YAM) client for Twisted.
Home-page: https://github.com/Weasyl/txyam2
Author: Brian Muller
Author-email: bamuller@gmail.com
License: MIT
Platform: UNKNOWN
Provides-Extra: sync
